passimapwidget/__init__.py
passimapwidget/passimapwidget.py
qtile_passimapwidget-0.1.0.dist-info/LICENSE
qtile_passimapwidget-0.1.0.dist-info/METADATA
qtile_passimapwidget-0.1.0.dist-info/WHEEL
qtile_passimapwidget-0.1.0.dist-info/top_level.txt
qtile_passimapwidget-0.1.0.dist-info/RECORD
